kgdt/__init__.py
kgdt/cli.py
kgdt/kgdt.py
kgdt/utils.py
kgdt/models/__init__.py
kgdt/models/doc.py
kgdt/models/graph.py
kgdt/neo4j/__init__.py
kgdt/neo4j/creator.py
kgdt/neo4j/factory.py
kgdt/neo4j/accessor/__init__.py
kgdt/neo4j/accessor/base.py
kgdt/neo4j/accessor/index.py
kgdt/neo4j/accessor/label.py
kgdt/neo4j/accessor/metadata.py
kgdt/pipeline/__init__.py
kgdt/pipeline/base.py
kgdt/pipeline/component/__init__.py
kgdt/pipeline/component/base.py
kgdt/pipeline/component/example.py
kgdt/pipeline/listener/__init__.py
kgdt/pipeline/listener/component_listener/__init__.py
kgdt/pipeline/listener/pipline_listener/__init__.py
kgdt/pipeline/listener/pipline_listener/saver.py
kgdt/retrieval/__init__.py
kgdt/retrieval/property/__init__.py
kgdt/retrieval/property/str_property_retrieval.py
kgdt/transfer/__init__.py
kgdt/transfer/neo4j.py
kgdt-0.3.1.dist-info/AUTHORS.rst
kgdt-0.3.1.dist-info/LICENSE
kgdt-0.3.1.dist-info/METADATA
kgdt-0.3.1.dist-info/WHEEL
kgdt-0.3.1.dist-info/entry_points.txt
kgdt-0.3.1.dist-info/top_level.txt
kgdt-0.3.1.dist-info/RECORD
