Metadata-Version: 2.1
Name: kgdt
Version: 0.3.1
Summary: a python library for create and operate on a knowledge graph in disk/neo4j/mysql.
Home-page: https://github.com/FudanSELab/kgdt
Author: Software Engineering Laboratory of Fudan University
Author-email: lmwtclmwtc@outlook.com
License: MIT license
Keywords: kgdt
Platform: UNKNOWN
Classifier: Development Status :: 2 - Pre-Alpha
Classifier: Intended Audience :: Developers
Classifier: License :: OSI Approved :: MIT License
Classifier: Natural Language :: English
Classifier: Programming Language :: Python :: 3
Classifier: Programming Language :: Python :: 3.6
Classifier: Programming Language :: Python :: 3.7
Classifier: Programming Language :: Python :: 3.8
Requires-Python: >=3.6
Requires-Dist: Click (>=7.0)
Requires-Dist: networkx (>=2.4)
Requires-Dist: numpy (>=1.18)
Requires-Dist: scipy (>=1.4.0)
Requires-Dist: smart-open
Requires-Dist: py2neo
